odoo/addons/purchase_request_order_approved/README.rst
odoo/addons/purchase_request_order_approved/__init__.py
odoo/addons/purchase_request_order_approved/__manifest__.py
odoo/addons/purchase_request_order_approved/init_hook.py
odoo/addons/purchase_request_order_approved/i18n/es.po
odoo/addons/purchase_request_order_approved/i18n/fr.po
odoo/addons/purchase_request_order_approved/i18n/nl_NL.po
odoo/addons/purchase_request_order_approved/i18n/purchase_request_order_approved.pot
odoo/addons/purchase_request_order_approved/i18n/purchase_request_to_rfq_order_approved.pot
odoo/addons/purchase_request_order_approved/i18n/sl.po
odoo/addons/purchase_request_order_approved/models/__init__.py
odoo/addons/purchase_request_order_approved/models/purchase_request.py
odoo/addons/purchase_request_order_approved/readme/CONTRIBUTORS.rst
odoo/addons/purchase_request_order_approved/readme/DESCRIPTION.rst
odoo/addons/purchase_request_order_approved/static/description/icon.png
odoo/addons/purchase_request_order_approved/static/description/index.html
odoo/addons/purchase_request_order_approved/tests/__init__.py
odoo/addons/purchase_request_order_approved/tests/test_purchase_request_order_approved.py
odoo/addons/purchase_request_order_approved/views/purchase_request_view.xml
odoo11_addon_purchase_request_order_approved-11.0.1.0.0.99.dev6.dist-info/METADATA
odoo11_addon_purchase_request_order_approved-11.0.1.0.0.99.dev6.dist-info/WHEEL
odoo11_addon_purchase_request_order_approved-11.0.1.0.0.99.dev6.dist-info/top_level.txt
odoo11_addon_purchase_request_order_approved-11.0.1.0.0.99.dev6.dist-info/RECORD
